maleo_transcription/__init__.py
maleo_transcription/constants.py
maleo_transcription/enums.py
maleo_transcription/models/__init__.py
maleo_transcription/models/responses.py
maleo_transcription/models/schemas.py
maleo_transcription/models/transfers/__init__.py
maleo_transcription/models/transfers/general.py
maleo_transcription/models/transfers/parameters.py
maleo_transcription/models/transfers/results.py
maleo_transcription/types/__init__.py
maleo_transcription/types/results.py
maleo_transcription-0.0.5.dist-info/METADATA
maleo_transcription-0.0.5.dist-info/WHEEL
maleo_transcription-0.0.5.dist-info/top_level.txt
maleo_transcription-0.0.5.dist-info/RECORD
