Metadata-Version: 2.4
Name: maleo-transcription
Version: 0.0.5
Summary: MaleoTranscription service package
Author-email: Agra Bima Yuda <agra@nexmedis.com>
License: MIT
Requires-Python: >=3.7
Requires-Dist: maleo_foundation>=0.3.31
